s2scat/__init__.py
s2scat/compression.py
s2scat/generation.py
s2scat/optimisation.py
s2scat/representation.py
s2scat/operators/__init__.py
s2scat/operators/matrices.py
s2scat/operators/spherical.py
s2scat/utility/__init__.py
s2scat/utility/config.py
s2scat/utility/normalisation.py
s2scat/utility/plotting.py
s2scat/utility/reorder.py
s2scat/utility/sampling.py
s2scat/utility/statistics.py
tests/__init__.py
tests/test_generator.py
tests/test_gradients.py
tests/test_scattering.py
s2scat-0.0.3.dist-info/LICENSE.txt
s2scat-0.0.3.dist-info/METADATA
s2scat-0.0.3.dist-info/WHEEL
s2scat-0.0.3.dist-info/top_level.txt
s2scat-0.0.3.dist-info/RECORD
