Metadata-Version: 2.1
Name: s2scat
Version: 0.0.3
Summary: Differentiable and GPU accelerated scattering covariance statistics on the sphere
Home-page: https://github.com/astro-informatics/s2scat
Author: Matthew A. Price, Louise Mousset, Erwan Allys, Jason D. McEwen
License: MIT
Classifier: Programming Language :: Python :: 3.8
Classifier: Programming Language :: Python :: 3.9
Classifier: Programming Language :: Python :: 3.10
Classifier: Programming Language :: Python :: 3.11
Classifier: Operating System :: OS Independent
Classifier: Intended Audience :: Developers
Classifier: Intended Audience :: Science/Research
Requires-Python: >=3.8
License-File: LICENSE.txt
Requires-Dist: numpy ==1.26.4
Requires-Dist: matplotlib ==3.8.4
Requires-Dist: optax
Requires-Dist: healpy ==1.16.6
Requires-Dist: s2wav >=1.0.4
Requires-Dist: s2fft >=1.1.1
